LICENSE
README.md
setup.cfg
setup.py
carefree_data.egg-info/PKG-INFO
carefree_data.egg-info/SOURCES.txt
carefree_data.egg-info/dependency_links.txt
carefree_data.egg-info/requires.txt
carefree_data.egg-info/top_level.txt
cfdata/__init__.py
cfdata/base.py
cfdata/types.py
cfdata/tabular/__init__.py
cfdata/tabular/api.py
cfdata/tabular/misc.py
cfdata/tabular/toolkit.py
cfdata/tabular/converters/__init__.py
cfdata/tabular/converters/base.py
cfdata/tabular/converters/categorical/__init__.py
cfdata/tabular/converters/categorical/core.py
cfdata/tabular/converters/numerical/__init__.py
cfdata/tabular/converters/numerical/core.py
cfdata/tabular/converters/string/__init__.py
cfdata/tabular/converters/string/core.py
cfdata/tabular/processors/__init__.py
cfdata/tabular/processors/base.py
cfdata/tabular/processors/function/__init__.py
cfdata/tabular/processors/function/core.py
cfdata/tabular/processors/identical/__init__.py
cfdata/tabular/processors/identical/core.py
cfdata/tabular/processors/logarithm/__init__.py
cfdata/tabular/processors/logarithm/core.py
cfdata/tabular/processors/min_max/__init__.py
cfdata/tabular/processors/min_max/core.py
cfdata/tabular/processors/normalize/__init__.py
cfdata/tabular/processors/normalize/core.py
cfdata/tabular/processors/one_hot/__init__.py
cfdata/tabular/processors/one_hot/core.py
cfdata/tabular/recognizer/__init__.py
cfdata/tabular/recognizer/core.py
cfdata/tabular/recognizer/binning/__init__.py
cfdata/tabular/recognizer/binning/base.py
cfdata/tabular/recognizer/binning/fuse.py
cfdata/tabular/recognizer/binning/identical.py
cfdata/tabular/recognizer/binning/opt.py