Metadata-Version: 2.1
Name: carefree-data
Version: 0.2.7
Summary: Data processing module implemented with numpy
Home-page: https://github.com/carefree0910/carefree-data
Author: carefree0910
Author-email: syameimaru.saki@gmail.com
License: UNKNOWN
Download-URL: https://github.com/carefree0910/carefree-data/archive/v0.2.7.tar.gz
Keywords: python numpy data-science
Platform: UNKNOWN
License-File: LICENSE
